ticos_agent/__init__.py
ticos_agent/__main__.py
ticos_agent/core/__init__.py
ticos_agent/core/agent.py
ticos_agent/core/config.py
ticos_agent/core/realtime_streamer.py
ticos_agent/core/robot.py
ticos_agent/core/telemetry.py
ticos_agent/robots/desktop/__init__.py
ticos_agent/robots/desktop/robot.py
ticos_agent/robots/yan/__init__.py
ticos_agent/robots/yan/robot.py
ticos_agent/services/__init__.py
ticos_agent/services/logger.py
ticos_agent/services/metrics_store.py
ticos_agent/utils/__init__.py
ticos_agent/utils/helpers.py
ticos_agent/utils/logger.py
ticos_agent/utils/telemetry_helpers.py
ticos_agent-0.5.4.dist-info/LICENSE
ticos_agent-0.5.4.dist-info/METADATA
ticos_agent-0.5.4.dist-info/WHEEL
ticos_agent-0.5.4.dist-info/entry_points.txt
ticos_agent-0.5.4.dist-info/RECORD
