Metadata-Version: 2.1
Name: ticos-agent
Version: 0.5.4
Summary: Ticos Agent - Bridges humanoid robots to Ticos
License: MIT
Author: Ticos Dev
Author-email: hi@tiwater.com
Requires-Python: >=3.5,<4.0
Classifier: License :: OSI Approved :: MIT License
Classifier: Programming Language :: Python :: 3
Classifier: Programming Language :: Python :: 3.5
Classifier: Programming Language :: Python :: 3.6
Classifier: Programming Language :: Python :: 3.7
Classifier: Programming Language :: Python :: 3.8
Classifier: Programming Language :: Python :: 3.9
Classifier: Programming Language :: Python :: 3.10
Classifier: Programming Language :: Python :: 3.11
Classifier: Programming Language :: Python :: 3.12
Provides-Extra: yan
Requires-Dist: numpy (>=1.18.5,<2.0.0)
Requires-Dist: opencv-python (>=4.2.0,<5.0.0)
Requires-Dist: psutil (>=5.7.0,<6.0.0)
Requires-Dist: pyaudio (>=0.2.11,<0.3.0)
Requires-Dist: pyyaml (>=5.3,<6.0)
Requires-Dist: requests (>=2.25.0,<3.0.0)
Requires-Dist: sounddevice (>=0.4.0,<0.5.0)
Requires-Dist: websockets (>=7.0,<8.0)
